helloasso_to_discourse.py
helloasso_to_discourse-0.4.dist-info/METADATA
helloasso_to_discourse-0.4.dist-info/WHEEL
helloasso_to_discourse-0.4.dist-info/entry_points.txt
helloasso_to_discourse-0.4.dist-info/top_level.txt
helloasso_to_discourse-0.4.dist-info/RECORD
