Metadata-Version: 2.1
Name: helloasso-to-discourse
Version: 0.4
Summary: Assign Discourse Badges to participants of HelloAsso events
Author-email: Julien Palard <julien@palard.fr>
License: MIT License
Requires-Dist: helloasso-apiv5
Requires-Dist: tabulate
Requires-Dist: requests
